elasticquerydsl/__init__.py
elasticquerydsl/base.py
elasticquerydsl/filter.py
elasticquerydsl/score.py
elasticquerydsl/utils/__init__.py
elasticquerydsl/utils/booldslbuilder.py
elasticquery_dsl_py-1.0.0.dist-info/LICENSE
elasticquery_dsl_py-1.0.0.dist-info/METADATA
elasticquery_dsl_py-1.0.0.dist-info/WHEEL
elasticquery_dsl_py-1.0.0.dist-info/top_level.txt
elasticquery_dsl_py-1.0.0.dist-info/RECORD
