Metadata-Version: 2.2
Name: elasticquery-dsl-py
Version: 1.0.0
Summary: A Python based DSL for building and managing Elasticsearch queries
Home-page: https://github.com/workindia/elasticquery-dsl-py
Author: Nikhil Kumar
Author-email: nikhil.kumar@workindia.in
License: MIT license
Classifier: Development Status :: 5 - Production/Stable
Classifier: License :: OSI Approved :: MIT License
Classifier: Natural Language :: English
Classifier: Programming Language :: Python :: 3
Classifier: Programming Language :: Python :: 3 :: Only
Classifier: Programming Language :: Python :: 3.6
Classifier: Programming Language :: Python :: 3.7
Classifier: Programming Language :: Python :: 3.8
Classifier: Programming Language :: Python :: 3.9
Classifier: Programming Language :: Python :: 3.10
Classifier: Programming Language :: Python :: 3.11
Classifier: Programming Language :: Python :: 3.12
Classifier: Operating System :: OS Independent
Requires-Python: >=3.6
License-File: LICENSE
Requires-Dist: typing-extensions
Provides-Extra: develop
Requires-Dist: typing-extensions; extra == "develop"
Requires-Dist: nox; extra == "develop"
Requires-Dist: pytest; extra == "develop"
Requires-Dist: pytest-cov; extra == "develop"
Requires-Dist: pre-commit; extra == "develop"
Requires-Dist: wheel; extra == "develop"
Requires-Dist: pip>=20; extra == "develop"
Requires-Dist: bump2version==1.0.0; extra == "develop"
Dynamic: author
Dynamic: author-email
Dynamic: classifier
Dynamic: description
Dynamic: description-content-type
Dynamic: home-page
Dynamic: license
Dynamic: provides-extra
Dynamic: requires-dist
Dynamic: requires-python
Dynamic: summary
